README.md
setup.py
adslproxy/__init__.py
adslproxy/__version__.py
adslproxy/cmd.py
adslproxy/db.py
adslproxy/settings.py
adslproxy/checker/__init__.py
adslproxy/checker/checker.py
adslproxy/sender/__init__.py
adslproxy/sender/sender.py
adslproxy/server/__init__.py
adslproxy/server/server.py
adslproxy_ota.egg-info/PKG-INFO
adslproxy_ota.egg-info/SOURCES.txt
adslproxy_ota.egg-info/dependency_links.txt
adslproxy_ota.egg-info/entry_points.txt
adslproxy_ota.egg-info/requires.txt
adslproxy_ota.egg-info/top_level.txt