Metadata-Version: 2.1
Name: adslproxy-ota
Version: 1.0.0
Summary: ADSL Proxy Pool Tool Forked from https://github.com/Python3WebSpider/ADSLProxy
Home-page: https://github.com/lxherman/AdslProxy
Author: Otavio
Author-email: otaviolxh@outlook.com
License: MIT
Platform: UNKNOWN
Classifier: License :: OSI Approved :: MIT License
Classifier: Programming Language :: Python :: 3.5
Classifier: Programming Language :: Python :: 3.6
Classifier: Programming Language :: Python :: 3.7
Classifier: Programming Language :: Python :: Implementation :: CPython
Classifier: Programming Language :: Python :: Implementation :: PyPy
Requires-Python: >=3.5.0
